<?xml version="1.0"?>
<!DOCTYPE source_file SYSTEM "apf.v5.1.1.dtd">
<source_file URI="VAR20001130.1100.1029.sgm" SOURCE="broadcast news" TYPE="text" AUTHOR="LDC" ENCODING="UTF-8">
<document DOCID="VAR20001130.1100.1029">
<entity ID="VAR20001130.1100.1029-E1" TYPE="GPE" SUBTYPE="Population-Center" CLASS="SPC">
  <entity_mention ID="VAR20001130.1100.1029-E1-2" TYPE="NOM" LDCTYPE="NOM" ROLE="LOC">
    <extent>
      <charseq START="370" END="384">العاصمة كولومبو</charseq>
    </extent>
    <head>
      <charseq START="370" END="376">العاصمة</charseq>
    </head>
  </entity_mention>
  <entity_mention ID="VAR20001130.1100.1029-E1-3" TYPE="NAM" LDCTYPE="NAM" ROLE="LOC">
    <extent>
      <charseq START="378" END="384">كولومبو</charseq>
    </extent>
    <head>
      <charseq START="378" END="384">كولومبو</charseq>
    </head>
  </entity_mention>
  <entity_attributes>
    <name NAME="كولومبو">
      <charseq START="378" END="384">كولومبو</charseq>
    </name>
  </entity_attributes>
</entity>
<entity ID="VAR20001130.1100.1029-E2" TYPE="PER" SUBTYPE="Group" CLASS="SPC">
  <entity_mention ID="VAR20001130.1100.1029-E2-5" TYPE="NOM" LDCTYPE="NOM">
    <extent>
      <charseq START="431" END="441">سبعة مدنيين</charseq>
    </extent>
    <head>
      <charseq START="436" END="441">مدنيين</charseq>
    </head>
  </entity_mention>
</entity>
<entity ID="VAR20001130.1100.1029-E3" TYPE="PER" SUBTYPE="Group" CLASS="SPC">
  <entity_mention ID="VAR20001130.1100.1029-E3-6" TYPE="NOM" LDCTYPE="NOM">
    <extent>
      <charseq START="450" END="466">سبعة وعشرين آخرين</charseq>
    </extent>
    <head>
      <charseq START="462" END="466">آخرين</charseq>
    </head>
  </entity_mention>
</entity>
<entity ID="VAR20001130.1100.1029-E4" TYPE="VEH" SUBTYPE="Land" CLASS="SPC">
  <entity_mention ID="VAR20001130.1100.1029-E4-7" TYPE="NOM" LDCTYPE="NOM">
    <extent>
      <charseq START="492" END="496">حافلة</charseq>
    </extent>
    <head>
      <charseq START="492" END="496">حافلة</charseq>
    </head>
  </entity_mention>
</entity>
<entity ID="VAR20001130.1100.1029-E5" TYPE="LOC" SUBTYPE="Region-General" CLASS="SPC">
  <entity_mention ID="VAR20001130.1100.1029-E5-8" TYPE="NOM" LDCTYPE="NOM">
    <extent>
      <charseq START="501" END="507">المنطقة</charseq>
    </extent>
    <head>
      <charseq START="501" END="507">المنطقة</charseq>
    </head>
  </entity_mention>
</entity>
<entity ID="VAR20001130.1100.1029-E6" TYPE="LOC" SUBTYPE="Region-General" CLASS="SPC">
  <entity_mention ID="VAR20001130.1100.1029-E6-13" TYPE="NOM" LDCTYPE="NOM">
    <extent>
      <charseq START="608" END="625">شمال
وشرق سيرلانكا</charseq>
    </extent>
    <head>
      <charseq START="618" END="625">سيرلانكا</charseq>
    </head>
  </entity_mention>
</entity>
<entity ID="VAR20001130.1100.1029-E7" TYPE="ORG" SUBTYPE="Non-Governmental" CLASS="SPC">
  <entity_mention ID="VAR20001130.1100.1029-E7-10" TYPE="NAM" LDCTYPE="NAM" LDCATR="FALSE" METONYMY_MENTION="TRUE">
    <extent>
      <charseq START="537" END="543">التاميل</charseq>
    </extent>
    <head>
      <charseq START="537" END="543">التاميل</charseq>
    </head>
  </entity_mention>
  <entity_mention ID="VAR20001130.1100.1029-E7-11" TYPE="PRO" LDCTYPE="PRO" LDCATR="FALSE">
    <extent>
      <charseq START="549" END="550">ون</charseq>
    </extent>
    <head>
      <charseq START="549" END="550">ون</charseq>
    </head>
  </entity_mention>
  <entity_mention ID="VAR20001130.1100.1029-E7-12" TYPE="NAM" LDCTYPE="NAM" LDCATR="TRUE">
    <extent>
      <charseq START="597" END="603">للتاميل</charseq>
    </extent>
    <head>
      <charseq START="597" END="603">للتاميل</charseq>
    </head>
  </entity_mention>
  <entity_mention ID="VAR20001130.1100.1029-E7-21" TYPE="NAM" LDCTYPE="NAM" LDCATR="FALSE" METONYMY_MENTION="TRUE">
    <extent>
      <charseq START="150" END="156">التاميل</charseq>
    </extent>
    <head>
      <charseq START="150" END="156">التاميل</charseq>
    </head>
  </entity_mention>
  <entity_attributes>
    <name NAME="للتاميل">
      <charseq START="597" END="603">للتاميل</charseq>
    </name>
  </entity_attributes>
</entity>
<entity ID="VAR20001130.1100.1029-E8" TYPE="GPE" SUBTYPE="Nation" CLASS="SPC">
  <entity_mention ID="VAR20001130.1100.1029-E8-1" TYPE="NAM" LDCTYPE="NAM" ROLE="LOC">
    <extent>
      <charseq START="68" END="75">سريلانكا</charseq>
    </extent>
    <head>
      <charseq START="68" END="75">سريلانكا</charseq>
    </head>
  </entity_mention>
  <entity_mention ID="VAR20001130.1100.1029-E8-23" TYPE="NOM" LDCTYPE="NOM" ROLE="LOC">
    <extent>
      <charseq START="192" END="197">البلاد</charseq>
    </extent>
    <head>
      <charseq START="192" END="197">البلاد</charseq>
    </head>
  </entity_mention>
  <entity_attributes>
    <name NAME="سريلانكا">
      <charseq START="68" END="75">سريلانكا</charseq>
    </name>
  </entity_attributes>
</entity>
<entity ID="VAR20001130.1100.1029-E9" TYPE="PER" SUBTYPE="Group" CLASS="SPC">
  <entity_mention ID="VAR20001130.1100.1029-E9-14" TYPE="NOM" LDCTYPE="NOM">
    <extent>
      <charseq START="81" END="89">سبعة جنود</charseq>
    </extent>
    <head>
      <charseq START="86" END="89">جنود</charseq>
    </head>
  </entity_mention>
</entity>
<entity ID="VAR20001130.1100.1029-E10" TYPE="PER" SUBTYPE="Individual" CLASS="SPC">
  <entity_mention ID="VAR20001130.1100.1029-E10-15" TYPE="NOM" LDCTYPE="NOM">
    <extent>
      <charseq START="92" END="100">مدني واحد</charseq>
    </extent>
    <head>
      <charseq START="92" END="95">مدني</charseq>
    </head>
  </entity_mention>
</entity>
<entity ID="VAR20001130.1100.1029-E11" TYPE="PER" SUBTYPE="Group" CLASS="SPC">
  <entity_mention ID="VAR20001130.1100.1029-E11-16" TYPE="PRO" LDCTYPE="PRO">
    <extent>
      <charseq START="116" END="117">هم</charseq>
    </extent>
    <head>
      <charseq START="116" END="117">هم</charseq>
    </head>
  </entity_mention>
</entity>
<entity ID="VAR20001130.1100.1029-E12" TYPE="WEA" SUBTYPE="Exploding" CLASS="SPC">
  <entity_mention ID="VAR20001130.1100.1029-E12-17" TYPE="NOM" LDCTYPE="NOM">
    <extent>
      <charseq START="129" END="136">لغم
أرضي</charseq>
    </extent>
    <head>
      <charseq START="129" END="131">لغم</charseq>
    </head>
  </entity_mention>
  <entity_mention ID="VAR20001130.1100.1029-E12-18" TYPE="PRO" LDCTYPE="PRO">
    <extent>
      <charseq START="141" END="141">ه</charseq>
    </extent>
    <head>
      <charseq START="141" END="141">ه</charseq>
    </head>
  </entity_mention>
</entity>
<entity ID="VAR20001130.1100.1029-E13" TYPE="PER" SUBTYPE="Group" CLASS="SPC">
  <entity_mention ID="VAR20001130.1100.1029-E13-4" TYPE="NOM" LDCTYPE="NOM">
    <extent>
      <charseq START="416" END="424">المتمردين</charseq>
    </extent>
    <head>
      <charseq START="416" END="424">المتمردين</charseq>
    </head>
  </entity_mention>
  <entity_mention ID="VAR20001130.1100.1029-E13-9" TYPE="NOM" LDCTYPE="NOM">
    <extent>
      <charseq START="530" END="543">متمردي التاميل</charseq>
    </extent>
    <head>
      <charseq START="530" END="535">متمردي</charseq>
    </head>
  </entity_mention>
  <entity_mention ID="VAR20001130.1100.1029-E13-20" TYPE="NOM" LDCTYPE="NOM">
    <extent>
      <charseq START="143" END="156">متمردو التاميل</charseq>
    </extent>
    <head>
      <charseq START="143" END="148">متمردو</charseq>
    </head>
  </entity_mention>
</entity>
<entity ID="VAR20001130.1100.1029-E15" TYPE="VEH" SUBTYPE="Land" CLASS="SPC">
  <entity_mention ID="VAR20001130.1100.1029-E15-22" TYPE="NOM" LDCTYPE="NOM">
    <extent>
      <charseq START="158" END="170">لحافلة عسكرية</charseq>
    </extent>
    <head>
      <charseq START="158" END="163">لحافلة</charseq>
    </head>
  </entity_mention>
</entity>
<entity ID="VAR20001130.1100.1029-E16" TYPE="LOC" SUBTYPE="Region-General" CLASS="SPC">
  <entity_mention ID="VAR20001130.1100.1029-E16-19" TYPE="NOM" LDCTYPE="NOM">
    <extent>
      <charseq START="175" END="214">الجزء الشمالي من البلاد التي
تمزقه الحرب</charseq>
    </extent>
    <head>
      <charseq START="175" END="179">الجزء</charseq>
    </head>
  </entity_mention>
  <entity_mention ID="VAR20001130.1100.1029-E16-24" TYPE="PRO" LDCTYPE="PRO">
    <extent>
      <charseq START="208" END="208">ه</charseq>
    </extent>
    <head>
      <charseq START="208" END="208">ه</charseq>
    </head>
  </entity_mention>
</entity>
<entity ID="VAR20001130.1100.1029-E17" TYPE="PER" SUBTYPE="Group" CLASS="SPC">
  <entity_mention ID="VAR20001130.1100.1029-E17-25" TYPE="NOM" LDCTYPE="NOM">
    <extent>
      <charseq START="222" END="236">مسئولون عسكريون</charseq>
    </extent>
    <head>
      <charseq START="222" END="228">مسئولون</charseq>
    </head>
  </entity_mention>
</entity>
<entity ID="VAR20001130.1100.1029-E18" TYPE="PER" SUBTYPE="Group" CLASS="SPC">
  <entity_mention ID="VAR20001130.1100.1029-E18-26" TYPE="NOM" LDCTYPE="NOM">
    <extent>
      <charseq START="247" END="257">عشرين جنديا</charseq>
    </extent>
    <head>
      <charseq START="253" END="257">جنديا</charseq>
    </head>
  </entity_mention>
  <entity_mention ID="VAR20001130.1100.1029-E18-27" TYPE="PRO" LDCTYPE="PRO">
    <extent>
      <charseq START="263" END="264">وا</charseq>
    </extent>
    <head>
      <charseq START="263" END="264">وا</charseq>
    </head>
  </entity_mention>
</entity>
<timex2 ID="VAR20001130.1100.1029-T1">
  <timex2_mention ID="VAR20001130.1100.1029-T1-1">
    <extent>
      <charseq START="307" END="316">صباح اليوم</charseq>
    </extent>
  </timex2_mention>
</timex2>
<timex2 ID="VAR20001130.1100.1029-T2">
  <timex2_mention ID="VAR20001130.1100.1029-T2-1">
    <extent>
      <charseq START="398" END="406">بعد يومين</charseq>
    </extent>
  </timex2_mention>
</timex2>
<timex2 ID="VAR20001130.1100.1029-T3">
  <timex2_mention ID="VAR20001130.1100.1029-T3-1">
    <extent>
      <charseq START="566" END="584">منذ ثمانية عشر عاما</charseq>
    </extent>
  </timex2_mention>
</timex2>
<timex2 ID="VAR20001130.1100.1029-T4">
  <timex2_mention ID="VAR20001130.1100.1029-T4-1">
    <extent>
      <charseq START="39" END="60">11/30/2000 11:17:09.02</charseq>
    </extent>
  </timex2_mention>
</timex2>
<relation ID="VAR20001130.1100.1029-R1" TYPE="PART-WHOLE" SUBTYPE="Geographical" TENSE="Present" MODALITY="Asserted">
  <relation_argument REFID="VAR20001130.1100.1029-E16" ROLE="Arg-1"/>
  <relation_argument REFID="VAR20001130.1100.1029-E8" ROLE="Arg-2"/>
  <relation_mention ID="VAR20001130.1100.1029-R1-1" LEXICALCONDITION="Preposition">
    <extent>
      <charseq START="175" END="214">الجزء الشمالي من البلاد التي
تمزقه الحرب</charseq>
    </extent>
    <relation_mention_argument REFID="VAR20001130.1100.1029-E16-19" ROLE="Arg-1">
      <extent>
        <charseq START="175" END="214">الجزء الشمالي من البلاد التي
تمزقه الحرب</charseq>
      </extent>
    </relation_mention_argument>
    <relation_mention_argument REFID="VAR20001130.1100.1029-E8-23" ROLE="Arg-2">
      <extent>
        <charseq START="192" END="197">البلاد</charseq>
      </extent>
    </relation_mention_argument>
  </relation_mention>
</relation>
<event ID="VAR20001130.1100.1029-EV1" TYPE="Life" SUBTYPE="Die" MODALITY="Asserted" POLARITY="Positive" GENERICITY="Specific" TENSE="Past">
  <event_argument REFID="VAR20001130.1100.1029-E12" ROLE="Instrument"/>
  <event_argument REFID="VAR20001130.1100.1029-E9" ROLE="Victim"/>
  <event_argument REFID="VAR20001130.1100.1029-E10" ROLE="Victim"/>
  <event_argument REFID="VAR20001130.1100.1029-E13" ROLE="Agent"/>
  <event_argument REFID="VAR20001130.1100.1029-E8" ROLE="Place"/>
  <event_mention ID="VAR20001130.1100.1029-EV1-1">
    <extent>
      <charseq START="68" END="156">سريلانكا لقي سبعة جنود ومدني واحد على الأقل مصرعهم في انفجار لغم
أرضي زرعه متمردو التاميل</charseq>
    </extent>
    <ldc_scope>
      <charseq START="65" END="214">في سريلانكا لقي سبعة جنود ومدني واحد على الأقل مصرعهم في انفجار لغم
أرضي زرعه متمردو التاميل لحافلة عسكرية في الجزء الشمالي من البلاد التي
تمزقه الحرب</charseq>
    </ldc_scope>
    <anchor>
      <charseq START="112" END="115">مصرع</charseq>
    </anchor>
    <event_mention_argument REFID="VAR20001130.1100.1029-E12-17" ROLE="Instrument">
      <extent>
        <charseq START="129" END="136">لغم
أرضي</charseq>
      </extent>
    </event_mention_argument>
    <event_mention_argument REFID="VAR20001130.1100.1029-E9-14" ROLE="Victim">
      <extent>
        <charseq START="81" END="89">سبعة جنود</charseq>
      </extent>
    </event_mention_argument>
    <event_mention_argument REFID="VAR20001130.1100.1029-E10-15" ROLE="Victim">
      <extent>
        <charseq START="92" END="100">مدني واحد</charseq>
      </extent>
    </event_mention_argument>
    <event_mention_argument REFID="VAR20001130.1100.1029-E13-20" ROLE="Agent">
      <extent>
        <charseq START="143" END="156">متمردو التاميل</charseq>
      </extent>
    </event_mention_argument>
    <event_mention_argument REFID="VAR20001130.1100.1029-E8-1" ROLE="Place">
      <extent>
        <charseq START="68" END="75">سريلانكا</charseq>
      </extent>
    </event_mention_argument>
  </event_mention>
</event>
<event ID="VAR20001130.1100.1029-EV2" TYPE="Conflict" SUBTYPE="Attack" MODALITY="Asserted" POLARITY="Positive" GENERICITY="Specific" TENSE="Past">
  <event_argument REFID="VAR20001130.1100.1029-E13" ROLE="Attacker"/>
  <event_argument REFID="VAR20001130.1100.1029-E9" ROLE="Target"/>
  <event_argument REFID="VAR20001130.1100.1029-E10" ROLE="Target"/>
  <event_argument REFID="VAR20001130.1100.1029-E12" ROLE="Instrument"/>
  <event_argument REFID="VAR20001130.1100.1029-E16" ROLE="Place"/>
  <event_mention ID="VAR20001130.1100.1029-EV2-1">
    <extent>
      <charseq START="81" END="214">سبعة جنود ومدني واحد على الأقل مصرعهم في انفجار لغم
أرضي زرعه متمردو التاميل لحافلة عسكرية في الجزء الشمالي من البلاد التي
تمزقه الحرب</charseq>
    </extent>
    <ldc_scope>
      <charseq START="65" END="214">في سريلانكا لقي سبعة جنود ومدني واحد على الأقل مصرعهم في انفجار لغم
أرضي زرعه متمردو التاميل لحافلة عسكرية في الجزء الشمالي من البلاد التي
تمزقه الحرب</charseq>
    </ldc_scope>
    <anchor>
      <charseq START="122" END="127">انفجار</charseq>
    </anchor>
    <event_mention_argument REFID="VAR20001130.1100.1029-E13-20" ROLE="Attacker">
      <extent>
        <charseq START="143" END="156">متمردو التاميل</charseq>
      </extent>
    </event_mention_argument>
    <event_mention_argument REFID="VAR20001130.1100.1029-E9-14" ROLE="Target">
      <extent>
        <charseq START="81" END="89">سبعة جنود</charseq>
      </extent>
    </event_mention_argument>
    <event_mention_argument REFID="VAR20001130.1100.1029-E10-15" ROLE="Target">
      <extent>
        <charseq START="92" END="100">مدني واحد</charseq>
      </extent>
    </event_mention_argument>
    <event_mention_argument REFID="VAR20001130.1100.1029-E12-17" ROLE="Instrument">
      <extent>
        <charseq START="129" END="136">لغم
أرضي</charseq>
      </extent>
    </event_mention_argument>
    <event_mention_argument REFID="VAR20001130.1100.1029-E16-19" ROLE="Place">
      <extent>
        <charseq START="175" END="214">الجزء الشمالي من البلاد التي
تمزقه الحرب</charseq>
      </extent>
    </event_mention_argument>
  </event_mention>
</event>
<event ID="VAR20001130.1100.1029-EV3" TYPE="Conflict" SUBTYPE="Attack" MODALITY="Asserted" POLARITY="Positive" GENERICITY="Specific" TENSE="Past">
  <event_argument REFID="VAR20001130.1100.1029-E13" ROLE="Attacker"/>
  <event_argument REFID="VAR20001130.1100.1029-E16" ROLE="Place"/>
  <event_mention ID="VAR20001130.1100.1029-EV3-1">
    <extent>
      <charseq START="143" END="214">متمردو التاميل لحافلة عسكرية في الجزء الشمالي من البلاد التي
تمزقه الحرب</charseq>
    </extent>
    <ldc_scope>
      <charseq START="65" END="214">في سريلانكا لقي سبعة جنود ومدني واحد على الأقل مصرعهم في انفجار لغم
أرضي زرعه متمردو التاميل لحافلة عسكرية في الجزء الشمالي من البلاد التي
تمزقه الحرب</charseq>
    </ldc_scope>
    <anchor>
      <charseq START="210" END="214">الحرب</charseq>
    </anchor>
    <event_mention_argument REFID="VAR20001130.1100.1029-E13-20" ROLE="Attacker">
      <extent>
        <charseq START="143" END="156">متمردو التاميل</charseq>
      </extent>
    </event_mention_argument>
    <event_mention_argument REFID="VAR20001130.1100.1029-E16-19" ROLE="Place">
      <extent>
        <charseq START="175" END="214">الجزء الشمالي من البلاد التي
تمزقه الحرب</charseq>
      </extent>
    </event_mention_argument>
  </event_mention>
</event>
<event ID="VAR20001130.1100.1029-EV4" TYPE="Life" SUBTYPE="Injure" MODALITY="Asserted" POLARITY="Positive" GENERICITY="Specific" TENSE="Past">
  <event_argument REFID="VAR20001130.1100.1029-E18" ROLE="Victim"/>
  <event_argument REFID="VAR20001130.1100.1029-E13" ROLE="Agent"/>
  <event_argument REFID="VAR20001130.1100.1029-E1" ROLE="Place"/>
  <event_argument REFID="VAR20001130.1100.1029-T1" ROLE="Time-Within"/>
  <event_mention ID="VAR20001130.1100.1029-EV4-1">
    <extent>
      <charseq START="247" END="424">عشرين جنديا أصيبوا بجراح
بعضها خطيرة في هذا الهجوم الذي وقع صباح اليوم على بعد حوالي مائتين
وعشرة كيلوا مترات إلى شمالي من العاصمة كولومبو وجاء الحادث بعد يومين
من قيام المتمردين</charseq>
    </extent>
    <ldc_scope>
      <charseq START="217" END="507">وقال مسئولون عسكريون إن حوالي عشرين جنديا أصيبوا بجراح
بعضها خطيرة في هذا الهجوم الذي وقع صباح اليوم على بعد حوالي مائتين
وعشرة كيلوا مترات إلى شمالي من العاصمة كولومبو وجاء الحادث بعد يومين
من قيام المتمردين بقتل سبعة مدنيين وإصابة سبعة وعشرين آخرين بجراح في
هجوم مماثل على حافلة في المنطقة</charseq>
    </ldc_scope>
    <anchor>
      <charseq START="266" END="270">بجراح</charseq>
    </anchor>
    <event_mention_argument REFID="VAR20001130.1100.1029-E18-26" ROLE="Victim">
      <extent>
        <charseq START="247" END="257">عشرين جنديا</charseq>
      </extent>
    </event_mention_argument>
    <event_mention_argument REFID="VAR20001130.1100.1029-E13-4" ROLE="Agent">
      <extent>
        <charseq START="416" END="424">المتمردين</charseq>
      </extent>
    </event_mention_argument>
    <event_mention_argument REFID="VAR20001130.1100.1029-E1-2" ROLE="Place">
      <extent>
        <charseq START="370" END="384">العاصمة كولومبو</charseq>
      </extent>
    </event_mention_argument>
    <event_mention_argument REFID="VAR20001130.1100.1029-T1-1" ROLE="Time-Within">
      <extent>
        <charseq START="307" END="316">صباح اليوم</charseq>
      </extent>
    </event_mention_argument>
  </event_mention>
</event>
<event ID="VAR20001130.1100.1029-EV5" TYPE="Conflict" SUBTYPE="Attack" MODALITY="Asserted" POLARITY="Positive" GENERICITY="Specific" TENSE="Past">
  <event_argument REFID="VAR20001130.1100.1029-E13" ROLE="Attacker"/>
  <event_argument REFID="VAR20001130.1100.1029-E1" ROLE="Place"/>
  <event_argument REFID="VAR20001130.1100.1029-E18" ROLE="Target"/>
  <event_argument REFID="VAR20001130.1100.1029-T1" ROLE="Time-Within"/>
  <event_mention ID="VAR20001130.1100.1029-EV5-1">
    <extent>
      <charseq START="247" END="424">عشرين جنديا أصيبوا بجراح
بعضها خطيرة في هذا الهجوم الذي وقع صباح اليوم على بعد حوالي مائتين
وعشرة كيلوا مترات إلى شمالي من العاصمة كولومبو وجاء الحادث بعد يومين
من قيام المتمردين</charseq>
    </extent>
    <ldc_scope>
      <charseq START="217" END="507">وقال مسئولون عسكريون إن حوالي عشرين جنديا أصيبوا بجراح
بعضها خطيرة في هذا الهجوم الذي وقع صباح اليوم على بعد حوالي مائتين
وعشرة كيلوا مترات إلى شمالي من العاصمة كولومبو وجاء الحادث بعد يومين
من قيام المتمردين بقتل سبعة مدنيين وإصابة سبعة وعشرين آخرين بجراح في
هجوم مماثل على حافلة في المنطقة</charseq>
    </ldc_scope>
    <anchor>
      <charseq START="291" END="296">الهجوم</charseq>
    </anchor>
    <event_mention_argument REFID="VAR20001130.1100.1029-E13-4" ROLE="Attacker">
      <extent>
        <charseq START="416" END="424">المتمردين</charseq>
      </extent>
    </event_mention_argument>
    <event_mention_argument REFID="VAR20001130.1100.1029-E1-2" ROLE="Place">
      <extent>
        <charseq START="370" END="384">العاصمة كولومبو</charseq>
      </extent>
    </event_mention_argument>
    <event_mention_argument REFID="VAR20001130.1100.1029-E18-26" ROLE="Target">
      <extent>
        <charseq START="247" END="257">عشرين جنديا</charseq>
      </extent>
    </event_mention_argument>
    <event_mention_argument REFID="VAR20001130.1100.1029-T1-1" ROLE="Time-Within">
      <extent>
        <charseq START="307" END="316">صباح اليوم</charseq>
      </extent>
    </event_mention_argument>
  </event_mention>
</event>
<event ID="VAR20001130.1100.1029-EV6" TYPE="Life" SUBTYPE="Die" MODALITY="Asserted" POLARITY="Positive" GENERICITY="Specific" TENSE="Past">
  <event_argument REFID="VAR20001130.1100.1029-E2" ROLE="Victim"/>
  <event_argument REFID="VAR20001130.1100.1029-E13" ROLE="Agent"/>
  <event_argument REFID="VAR20001130.1100.1029-E5" ROLE="Place"/>
  <event_mention ID="VAR20001130.1100.1029-EV6-1">
    <extent>
      <charseq START="416" END="507">المتمردين بقتل سبعة مدنيين وإصابة سبعة وعشرين آخرين بجراح في
هجوم مماثل على حافلة في المنطقة</charseq>
    </extent>
    <ldc_scope>
      <charseq START="217" END="507">وقال مسئولون عسكريون إن حوالي عشرين جنديا أصيبوا بجراح
بعضها خطيرة في هذا الهجوم الذي وقع صباح اليوم على بعد حوالي مائتين
وعشرة كيلوا مترات إلى شمالي من العاصمة كولومبو وجاء الحادث بعد يومين
من قيام المتمردين بقتل سبعة مدنيين وإصابة سبعة وعشرين آخرين بجراح في
هجوم مماثل على حافلة في المنطقة</charseq>
    </ldc_scope>
    <anchor>
      <charseq START="426" END="429">بقتل</charseq>
    </anchor>
    <event_mention_argument REFID="VAR20001130.1100.1029-E2-5" ROLE="Victim">
      <extent>
        <charseq START="431" END="441">سبعة مدنيين</charseq>
      </extent>
    </event_mention_argument>
    <event_mention_argument REFID="VAR20001130.1100.1029-E13-4" ROLE="Agent">
      <extent>
        <charseq START="416" END="424">المتمردين</charseq>
      </extent>
    </event_mention_argument>
    <event_mention_argument REFID="VAR20001130.1100.1029-E5-8" ROLE="Place">
      <extent>
        <charseq START="501" END="507">المنطقة</charseq>
      </extent>
    </event_mention_argument>
  </event_mention>
</event>
<event ID="VAR20001130.1100.1029-EV7" TYPE="Life" SUBTYPE="Injure" MODALITY="Asserted" POLARITY="Positive" GENERICITY="Specific" TENSE="Past">
  <event_argument REFID="VAR20001130.1100.1029-E3" ROLE="Victim"/>
  <event_argument REFID="VAR20001130.1100.1029-E13" ROLE="Agent"/>
  <event_argument REFID="VAR20001130.1100.1029-E5" ROLE="Place"/>
  <event_mention ID="VAR20001130.1100.1029-EV7-1">
    <extent>
      <charseq START="416" END="507">المتمردين بقتل سبعة مدنيين وإصابة سبعة وعشرين آخرين بجراح في
هجوم مماثل على حافلة في المنطقة</charseq>
    </extent>
    <ldc_scope>
      <charseq START="217" END="507">وقال مسئولون عسكريون إن حوالي عشرين جنديا أصيبوا بجراح
بعضها خطيرة في هذا الهجوم الذي وقع صباح اليوم على بعد حوالي مائتين
وعشرة كيلوا مترات إلى شمالي من العاصمة كولومبو وجاء الحادث بعد يومين
من قيام المتمردين بقتل سبعة مدنيين وإصابة سبعة وعشرين آخرين بجراح في
هجوم مماثل على حافلة في المنطقة</charseq>
    </ldc_scope>
    <anchor>
      <charseq START="468" END="472">بجراح</charseq>
    </anchor>
    <event_mention_argument REFID="VAR20001130.1100.1029-E3-6" ROLE="Victim">
      <extent>
        <charseq START="450" END="466">سبعة وعشرين آخرين</charseq>
      </extent>
    </event_mention_argument>
    <event_mention_argument REFID="VAR20001130.1100.1029-E13-4" ROLE="Agent">
      <extent>
        <charseq START="416" END="424">المتمردين</charseq>
      </extent>
    </event_mention_argument>
    <event_mention_argument REFID="VAR20001130.1100.1029-E5-8" ROLE="Place">
      <extent>
        <charseq START="501" END="507">المنطقة</charseq>
      </extent>
    </event_mention_argument>
  </event_mention>
</event>
<event ID="VAR20001130.1100.1029-EV8" TYPE="Conflict" SUBTYPE="Attack" MODALITY="Asserted" POLARITY="Positive" GENERICITY="Specific" TENSE="Past">
  <event_argument REFID="VAR20001130.1100.1029-E13" ROLE="Attacker"/>
  <event_argument REFID="VAR20001130.1100.1029-E5" ROLE="Place"/>
  <event_argument REFID="VAR20001130.1100.1029-E3" ROLE="Target"/>
  <event_mention ID="VAR20001130.1100.1029-EV8-1">
    <extent>
      <charseq START="416" END="507">المتمردين بقتل سبعة مدنيين وإصابة سبعة وعشرين آخرين بجراح في
هجوم مماثل على حافلة في المنطقة</charseq>
    </extent>
    <ldc_scope>
      <charseq START="217" END="507">وقال مسئولون عسكريون إن حوالي عشرين جنديا أصيبوا بجراح
بعضها خطيرة في هذا الهجوم الذي وقع صباح اليوم على بعد حوالي مائتين
وعشرة كيلوا مترات إلى شمالي من العاصمة كولومبو وجاء الحادث بعد يومين
من قيام المتمردين بقتل سبعة مدنيين وإصابة سبعة وعشرين آخرين بجراح في
هجوم مماثل على حافلة في المنطقة</charseq>
    </ldc_scope>
    <anchor>
      <charseq START="477" END="480">هجوم</charseq>
    </anchor>
    <event_mention_argument REFID="VAR20001130.1100.1029-E13-4" ROLE="Attacker">
      <extent>
        <charseq START="416" END="424">المتمردين</charseq>
      </extent>
    </event_mention_argument>
    <event_mention_argument REFID="VAR20001130.1100.1029-E5-8" ROLE="Place">
      <extent>
        <charseq START="501" END="507">المنطقة</charseq>
      </extent>
    </event_mention_argument>
    <event_mention_argument REFID="VAR20001130.1100.1029-E3-6" ROLE="Target">
      <extent>
        <charseq START="450" END="466">سبعة وعشرين آخرين</charseq>
      </extent>
    </event_mention_argument>
  </event_mention>
</event>
<event ID="VAR20001130.1100.1029-EV9" TYPE="Conflict" SUBTYPE="Attack" MODALITY="Asserted" POLARITY="Positive" GENERICITY="Specific" TENSE="Past">
  <event_argument REFID="VAR20001130.1100.1029-E13" ROLE="Attacker"/>
  <event_argument REFID="VAR20001130.1100.1029-E6" ROLE="Place"/>
  <event_argument REFID="VAR20001130.1100.1029-T3" ROLE="Time-Starting"/>
  <event_mention ID="VAR20001130.1100.1029-EV9-1">
    <extent>
      <charseq START="530" END="625">متمردي التاميل
يخوضون حربا انفصالية منذ ثمانية عشر عاما لإنشاء وطن للتاميل في شمال
وشرق سيرلانكا</charseq>
    </extent>
    <ldc_scope>
      <charseq START="510" END="625">تجدر الإشارة إلى أن متمردي التاميل
يخوضون حربا انفصالية منذ ثمانية عشر عاما لإنشاء وطن للتاميل في شمال
وشرق سيرلانكا</charseq>
    </ldc_scope>
    <anchor>
      <charseq START="552" END="555">حربا</charseq>
    </anchor>
    <event_mention_argument REFID="VAR20001130.1100.1029-E13-9" ROLE="Attacker">
      <extent>
        <charseq START="530" END="543">متمردي التاميل</charseq>
      </extent>
    </event_mention_argument>
    <event_mention_argument REFID="VAR20001130.1100.1029-E6-13" ROLE="Place">
      <extent>
        <charseq START="608" END="625">شمال
وشرق سيرلانكا</charseq>
      </extent>
    </event_mention_argument>
    <event_mention_argument REFID="VAR20001130.1100.1029-T3-1" ROLE="Time-Starting">
      <extent>
        <charseq START="566" END="584">منذ ثمانية عشر عاما</charseq>
      </extent>
    </event_mention_argument>
  </event_mention>
</event>
</document>
</source_file>
